Workbook

Sheet Nota spese
A1: NOTA SPESE MENSILE — TRASFERTE AMMINISTRATORE
A2: Overall Group S.r.l. — compilare solo le celle gialle. Istruzioni nel foglio «Istruzioni».
A4: Beneficiario | C4: Pradella Tazio
A5: Ruolo | C5: Presidente CdA
A6: Mese di riferimento | C6: 46082
A7: Sede di lavoro (comune) | C7: Villafranca di Verona
A8: Comune di residenza | C8: Verona
A9: Veicolo (marca e modello) | C9: da compilare
A10: Targa | C10: da compilare
A11: Tariffa ACI €/km del veicolo | C11: 0.45
A12: Fonte tariffa | C12: Tabelle ACI 2026, modello del veicolo
A13: Altri nomi e frazioni del comune della sede (separati da virgola) | C13: Villafranca,Alpo,Caluri,Dossobuono,Pizzoletta,Quaderni,Rizza,Rosegaferro
A15: Data | B15: Cliente | C15: Commessa / fattura n. | D15: Motivo della trasferta | E15: Partenza (comune) | F15: Destinazione (comune) | G15: Km andata e ritorno | H15: Rimborso km (€) | I15: Pedaggi (€) | J15: Parcheggi (€) | K15: Vitto (€) | L15: Alloggio (€) | M15: Taxi / treno / bus (€) | N15: Pagato con mezzo tracciabile (S/N) | O15: N. allegati | P15: Totale riga (€) | Q15: Controllo
A16: 46093 | B16: Rossi S.r.l. (ESEMPIO: cancellare) | C16: FatturaLab 2026/123 | D16: Sopralluogo aggiornamento DVR | E16: Villafranca di Verona | F16: Vicenza | G16: 150 | H16: =IF(G16="","",ROUND(G16*$C$11,2)) | I16: 10.4 | J16: 0 | K16: 18 | L16: 0 | M16: 0 | N16: S | O16: 3 | P16: =IF(A16="","",N(H16)+SUM(I16:M16)) | Q16: =IF(A16="","",IF(ISNUMBER(SEARCH("ESEMPIO",B16)),"ESEMPIO: cancellare la riga",IF(OR(F16="",C16=""),"MANCA destinazione o commessa",IF(OR(LOWER(TRIM(F16))=LOWER(TRIM($C$7)),ISNUMBER(SEARCH(","&LOWER(TRIM(F16))&",",","&LOWER(SUBSTITUTE($C$13," ",""))&","))),"NO: trasferta nel comune della sede (o frazione)",IF(AND(SUM(K16:M16)>0,UPPER(N16)<>"S"),"NO: vitto/alloggio/taxi non tracciabile",IF(O16<1,"MANCA allegato","OK"))))))
H17: =IF(G17="","",ROUND(G17*$C$11,2)) | P17: =IF(A17="","",N(H17)+SUM(I17:M17)) | Q17: =IF(A17="","",IF(ISNUMBER(SEARCH("ESEMPIO",B17)),"ESEMPIO: cancellare la riga",IF(OR(F17="",C17=""),"MANCA destinazione o commessa",IF(OR(LOWER(TRIM(F17))=LOWER(TRIM($C$7)),ISNUMBER(SEARCH(","&LOWER(TRIM(F17))&",",","&LOWER(SUBSTITUTE($C$13," ",""))&","))),"NO: trasferta nel comune della sede (o frazione)",IF(AND(SUM(K17:M17)>0,UPPER(N17)<>"S"),"NO: vitto/alloggio/taxi non tracciabile",IF(O17<1,"MANCA allegato","OK"))))))
H18: =IF(G18="","",ROUND(G18*$C$11,2)) | P18: =IF(A18="","",N(H18)+SUM(I18:M18)) | Q18: =IF(A18="","",IF(ISNUMBER(SEARCH("ESEMPIO",B18)),"ESEMPIO: cancellare la riga",IF(OR(F18="",C18=""),"MANCA destinazione o commessa",IF(OR(LOWER(TRIM(F18))=LOWER(TRIM($C$7)),ISNUMBER(SEARCH(","&LOWER(TRIM(F18))&",",","&LOWER(SUBSTITUTE($C$13," ",""))&","))),"NO: trasferta nel comune della sede (o frazione)",IF(AND(SUM(K18:M18)>0,UPPER(N18)<>"S"),"NO: vitto/alloggio/taxi non tracciabile",IF(O18<1,"MANCA allegato","OK"))))))
H19: =IF(G19="","",ROUND(G19*$C$11,2)) | P19: =IF(A19="","",N(H19)+SUM(I19:M19)) | Q19: =IF(A19="","",IF(ISNUMBER(SEARCH("ESEMPIO",B19)),"ESEMPIO: cancellare la riga",IF(OR(F19="",C19=""),"MANCA destinazione o commessa",IF(OR(LOWER(TRIM(F19))=LOWER(TRIM($C$7)),ISNUMBER(SEARCH(","&LOWER(TRIM(F19))&",",","&LOWER(SUBSTITUTE($C$13," ",""))&","))),"NO: trasferta nel comune della sede (o frazione)",IF(AND(SUM(K19:M19)>0,UPPER(N19)<>"S"),"NO: vitto/alloggio/taxi non tracciabile",IF(O19<1,"MANCA allegato","OK"))))))
H20: =IF(G20="","",ROUND(G20*$C$11,2)) | P20: =IF(A20="","",N(H20)+SUM(I20:M20)) | Q20: =IF(A20="","",IF(ISNUMBER(SEARCH("ESEMPIO",B20)),"ESEMPIO: cancellare la riga",IF(OR(F20="",C20=""),"MANCA destinazione o commessa",IF(OR(LOWER(TRIM(F20))=LOWER(TRIM($C$7)),ISNUMBER(SEARCH(","&LOWER(TRIM(F20))&",",","&LOWER(SUBSTITUTE($C$13," ",""))&","))),"NO: trasferta nel comune della sede (o frazione)",IF(AND(SUM(K20:M20)>0,UPPER(N20)<>"S"),"NO: vitto/alloggio/taxi non tracciabile",IF(O20<1,"MANCA allegato","OK"))))))
H21: =IF(G21="","",ROUND(G21*$C$11,2)) | P21: =IF(A21="","",N(H21)+SUM(I21:M21)) | Q21: =IF(A21="","",IF(ISNUMBER(SEARCH("ESEMPIO",B21)),"ESEMPIO: cancellare la riga",IF(OR(F21="",C21=""),"MANCA destinazione o commessa",IF(OR(LOWER(TRIM(F21))=LOWER(TRIM($C$7)),ISNUMBER(SEARCH(","&LOWER(TRIM(F21))&",",","&LOWER(SUBSTITUTE($C$13," ",""))&","))),"NO: trasferta nel comune della sede (o frazione)",IF(AND(SUM(K21:M21)>0,UPPER(N21)<>"S"),"NO: vitto/alloggio/taxi non tracciabile",IF(O21<1,"MANCA allegato","OK"))))))
H22: =IF(G22="","",ROUND(G22*$C$11,2)) | P22: =IF(A22="","",N(H22)+SUM(I22:M22)) | Q22: =IF(A22="","",IF(ISNUMBER(SEARCH("ESEMPIO",B22)),"ESEMPIO: cancellare la riga",IF(OR(F22="",C22=""),"MANCA destinazione o commessa",IF(OR(LOWER(TRIM(F22))=LOWER(TRIM($C$7)),ISNUMBER(SEARCH(","&LOWER(TRIM(F22))&",",","&LOWER(SUBSTITUTE($C$13," ",""))&","))),"NO: trasferta nel comune della sede (o frazione)",IF(AND(SUM(K22:M22)>0,UPPER(N22)<>"S"),"NO: vitto/alloggio/taxi non tracciabile",IF(O22<1,"MANCA allegato","OK"))))))
H23: =IF(G23="","",ROUND(G23*$C$11,2)) | P23: =IF(A23="","",N(H23)+SUM(I23:M23)) | Q23: =IF(A23="","",IF(ISNUMBER(SEARCH("ESEMPIO",B23)),"ESEMPIO: cancellare la riga",IF(OR(F23="",C23=""),"MANCA destinazione o commessa",IF(OR(LOWER(TRIM(F23))=LOWER(TRIM($C$7)),ISNUMBER(SEARCH(","&LOWER(TRIM(F23))&",",","&LOWER(SUBSTITUTE($C$13," ",""))&","))),"NO: trasferta nel comune della sede (o frazione)",IF(AND(SUM(K23:M23)>0,UPPER(N23)<>"S"),"NO: vitto/alloggio/taxi non tracciabile",IF(O23<1,"MANCA allegato","OK"))))))
H24: =IF(G24="","",ROUND(G24*$C$11,2)) | P24: =IF(A24="","",N(H24)+SUM(I24:M24)) | Q24: =IF(A24="","",IF(ISNUMBER(SEARCH("ESEMPIO",B24)),"ESEMPIO: cancellare la riga",IF(OR(F24="",C24=""),"MANCA destinazione o commessa",IF(OR(LOWER(TRIM(F24))=LOWER(TRIM($C$7)),ISNUMBER(SEARCH(","&LOWER(TRIM(F24))&",",","&LOWER(SUBSTITUTE($C$13," ",""))&","))),"NO: trasferta nel comune della sede (o frazione)",IF(AND(SUM(K24:M24)>0,UPPER(N24)<>"S"),"NO: vitto/alloggio/taxi non tracciabile",IF(O24<1,"MANCA allegato","OK"))))))
H25: =IF(G25="","",ROUND(G25*$C$11,2)) | P25: =IF(A25="","",N(H25)+SUM(I25:M25)) | Q25: =IF(A25="","",IF(ISNUMBER(SEARCH("ESEMPIO",B25)),"ESEMPIO: cancellare la riga",IF(OR(F25="",C25=""),"MANCA destinazione o commessa",IF(OR(LOWER(TRIM(F25))=LOWER(TRIM($C$7)),ISNUMBER(SEARCH(","&LOWER(TRIM(F25))&",",","&LOWER(SUBSTITUTE($C$13," ",""))&","))),"NO: trasferta nel comune della sede (o frazione)",IF(AND(SUM(K25:M25)>0,UPPER(N25)<>"S"),"NO: vitto/alloggio/taxi non tracciabile",IF(O25<1,"MANCA allegato","OK"))))))
H26: =IF(G26="","",ROUND(G26*$C$11,2)) | P26: =IF(A26="","",N(H26)+SUM(I26:M26)) | Q26: =IF(A26="","",IF(ISNUMBER(SEARCH("ESEMPIO",B26)),"ESEMPIO: cancellare la riga",IF(OR(F26="",C26=""),"MANCA destinazione o commessa",IF(OR(LOWER(TRIM(F26))=LOWER(TRIM($C$7)),ISNUMBER(SEARCH(","&LOWER(TRIM(F26))&",",","&LOWER(SUBSTITUTE($C$13," ",""))&","))),"NO: trasferta nel comune della sede (o frazione)",IF(AND(SUM(K26:M26)>0,UPPER(N26)<>"S"),"NO: vitto/alloggio/taxi non tracciabile",IF(O26<1,"MANCA allegato","OK"))))))
H27: =IF(G27="","",ROUND(G27*$C$11,2)) | P27: =IF(A27="","",N(H27)+SUM(I27:M27)) | Q27: =IF(A27="","",IF(ISNUMBER(SEARCH("ESEMPIO",B27)),"ESEMPIO: cancellare la riga",IF(OR(F27="",C27=""),"MANCA destinazione o commessa",IF(OR(LOWER(TRIM(F27))=LOWER(TRIM($C$7)),ISNUMBER(SEARCH(","&LOWER(TRIM(F27))&",",","&LOWER(SUBSTITUTE($C$13," ",""))&","))),"NO: trasferta nel comune della sede (o frazione)",IF(AND(SUM(K27:M27)>0,UPPER(N27)<>"S"),"NO: vitto/alloggio/taxi non tracciabile",IF(O27<1,"MANCA allegato","OK"))))))
H28: =IF(G28="","",ROUND(G28*$C$11,2)) | P28: =IF(A28="","",N(H28)+SUM(I28:M28)) | Q28: =IF(A28="","",IF(ISNUMBER(SEARCH("ESEMPIO",B28)),"ESEMPIO: cancellare la riga",IF(OR(F28="",C28=""),"MANCA destinazione o commessa",IF(OR(LOWER(TRIM(F28))=LOWER(TRIM($C$7)),ISNUMBER(SEARCH(","&LOWER(TRIM(F28))&",",","&LOWER(SUBSTITUTE($C$13," ",""))&","))),"NO: trasferta nel comune della sede (o frazione)",IF(AND(SUM(K28:M28)>0,UPPER(N28)<>"S"),"NO: vitto/alloggio/taxi non tracciabile",IF(O28<1,"MANCA allegato","OK"))))))
... H40: =IF(G40="","",ROUND(G40*$C$11,2)) | P40: =IF(A40="","",N(H40)+SUM(I40:M40)) | Q40: =IF(A40="","",IF(ISNUMBER(SEARCH("ESEMPIO",B40)),"ESEMPIO: cancellare la riga",IF(OR(F40="",C40=""),"MANCA destinazione o commessa",IF(OR(LOWER(TRIM(F40))=LOWER(TRIM($C$7)),ISNUMBER(SEARCH(","&LOWER(TRIM(F40))&",",","&LOWER(SUBSTITUTE($C$13," ",""))&","))),"NO: trasferta nel comune della sede (o frazione)",IF(AND(SUM(K40:M40)>0,UPPER(N40)<>"S"),"NO: vitto/alloggio/taxi non tracciabile",IF(O40<1,"MANCA allegato","OK"))))))
F42: TOTALI | G42: =SUM(G16:G40) | H42: =SUM(H16:H40) | I42: =SUM(I16:I40) | J42: =SUM(J16:J40) | K42: =SUM(K16:K40) | L42: =SUM(L16:L40) | M42: =SUM(M16:M40) | P42: =SUM(P16:P40)
F43: TOTALE RIMBORSABILE (solo righe OK) | P43: =SUMIFS(P16:P40,Q16:Q40,"OK")
F44: Righe da correggere prima dell'approvazione | P44: =SUMPRODUCT((Q16:Q40<>"")*(LEFT(Q16:Q40,2)<>"OK"))
A47: Firma del beneficiario e data
A49: Approvato da (altro amministratore), firma e data
A51: Pagato con bonifico il / CRO
A53: Riportato nel cedolino del mese, voce

Sheet Nota forfettaria
A1: NOTA SPESE MENSILE — INDENNITÀ FORFETTARIA DI TRASFERTA
A2: Alternativa al foglio «Nota spese»: solo per rimborsare trasferte reali, e solo se il regolamento trasferte approvato dai soci prevede l'indennità forfettaria. Non è un'integrazione del compenso.
A4: Beneficiario | C4: ='Nota spese'!C4
A5: Mese di riferimento | C5: ='Nota spese'!C6
A6: Sede di lavoro (comune) | C6: ='Nota spese'!C7
A7: Tariffa ACI €/km del veicolo | C7: ='Nota spese'!C11
A8: Indennità giornaliera da regolamento (€) | C8: 46.48
A9: Soglia esente: nessun rimborso vitto/alloggio (€) | C9: 46.48 | D9: Art. 51, c. 5, TUIR: soglie per trasferte in Italia fuori dal comune della sede di lavoro.
A10: Soglia esente: rimborsato vitto OPPURE alloggio (€) | C10: 30.99
A11: Soglia esente: rimborsati vitto E alloggio (€) | C11: 15.49
A12: Altri nomi e frazioni del comune della sede | C12: ='Nota spese'!C13
A14: Data | B14: Cliente | C14: Commessa / fattura n. | D14: Motivo della trasferta | E14: Partenza (comune) | F14: Destinazione (comune) | G14: Km andata e ritorno | H14: Rimborso km (€) | I14: Pedaggi (€) | J14: Parcheggi (€) | K14: Vitto rimborsato a parte (€) | L14: Alloggio rimborsato a parte (€) | M14: Vitto/alloggio pagati tracciabili (S/N) | N14: Indennità del giorno (€) | O14: di cui esente (€) | P14: di cui imponibile in cedolino (€) | Q14: N. allegati | R14: Totale riga (€) | S14: Controllo
A15: 46093 | B15: Rossi S.r.l. (ESEMPIO: cancellare) | C15: FatturaLab 2026/123 | D15: Sopralluogo aggiornamento DVR | E15: Villafranca di Verona | F15: Vicenza | G15: 150 | H15: =IF(G15="","",G15*$C$7) | I15: 10.4 | J15: 0 | K15: 0 | L15: 0 | N15: =IF(A15="","",IF(COUNTIF($A$15:A15,A15)=1,$C$8,0)) | O15: =IF(A15="","",MIN(N15,IF(AND(SUMIF($A$15:$A$39,A15,$K$15:$K$39)>0,SUMIF($A$15:$A$39,A15,$L$15:$L$39)>0),$C$11,IF(OR(SUMIF($A$15:$A$39,A15,$K$15:$K$39)>0,SUMIF($A$15:$A$39,A15,$L$15:$L$39)>0),$C$10,$C$9)))) | P15: =IF(A15="","",N15-O15) | Q15: 2 | R15: =IF(A15="","",N(H15)+N(I15)+N(J15)+N(K15)+N(L15)+N15) | S15: =IF(A15="","",IF(ISNUMBER(SEARCH("ESEMPIO",B15)),"ESEMPIO: cancellare la riga",IF(OR(F15="",C15=""),"MANCA destinazione o commessa",IF(OR(LOWER(TRIM(F15))=LOWER(TRIM($C$6)),ISNUMBER(SEARCH(","&LOWER(TRIM(F15))&",",","&LOWER(SUBSTITUTE($C$12," ",""))&","))),"NO: trasferta nel comune della sede (o frazione)",IF(AND(N(K15)+N(L15)>0,UPPER(M15)<>"S"),"NO: vitto/alloggio non tracciabile",IF(Q15<1,"MANCA prova della trasferta","OK"))))))
H16: =IF(G16="","",G16*$C$7) | N16: =IF(A16="","",IF(COUNTIF($A$15:A16,A16)=1,$C$8,0)) | O16: =IF(A16="","",MIN(N16,IF(AND(SUMIF($A$15:$A$39,A16,$K$15:$K$39)>0,SUMIF($A$15:$A$39,A16,$L$15:$L$39)>0),$C$11,IF(OR(SUMIF($A$15:$A$39,A16,$K$15:$K$39)>0,SUMIF($A$15:$A$39,A16,$L$15:$L$39)>0),$C$10,$C$9)))) | P16: =IF(A16="","",N16-O16) | R16: =IF(A16="","",N(H16)+N(I16)+N(J16)+N(K16)+N(L16)+N16) | S16: =IF(A16="","",IF(ISNUMBER(SEARCH("ESEMPIO",B16)),"ESEMPIO: cancellare la riga",IF(OR(F16="",C16=""),"MANCA destinazione o commessa",IF(OR(LOWER(TRIM(F16))=LOWER(TRIM($C$6)),ISNUMBER(SEARCH(","&LOWER(TRIM(F16))&",",","&LOWER(SUBSTITUTE($C$12," ",""))&","))),"NO: trasferta nel comune della sede (o frazione)",IF(AND(N(K16)+N(L16)>0,UPPER(M16)<>"S"),"NO: vitto/alloggio non tracciabile",IF(Q16<1,"MANCA prova della trasferta","OK"))))))
H17: =IF(G17="","",G17*$C$7) | N17: =IF(A17="","",IF(COUNTIF($A$15:A17,A17)=1,$C$8,0)) | O17: =IF(A17="","",MIN(N17,IF(AND(SUMIF($A$15:$A$39,A17,$K$15:$K$39)>0,SUMIF($A$15:$A$39,A17,$L$15:$L$39)>0),$C$11,IF(OR(SUMIF($A$15:$A$39,A17,$K$15:$K$39)>0,SUMIF($A$15:$A$39,A17,$L$15:$L$39)>0),$C$10,$C$9)))) | P17: =IF(A17="","",N17-O17) | R17: =IF(A17="","",N(H17)+N(I17)+N(J17)+N(K17)+N(L17)+N17) | S17: =IF(A17="","",IF(ISNUMBER(SEARCH("ESEMPIO",B17)),"ESEMPIO: cancellare la riga",IF(OR(F17="",C17=""),"MANCA destinazione o commessa",IF(OR(LOWER(TRIM(F17))=LOWER(TRIM($C$6)),ISNUMBER(SEARCH(","&LOWER(TRIM(F17))&",",","&LOWER(SUBSTITUTE($C$12," ",""))&","))),"NO: trasferta nel comune della sede (o frazione)",IF(AND(N(K17)+N(L17)>0,UPPER(M17)<>"S"),"NO: vitto/alloggio non tracciabile",IF(Q17<1,"MANCA prova della trasferta","OK"))))))
H18: =IF(G18="","",G18*$C$7) | N18: =IF(A18="","",IF(COUNTIF($A$15:A18,A18)=1,$C$8,0)) | O18: =IF(A18="","",MIN(N18,IF(AND(SUMIF($A$15:$A$39,A18,$K$15:$K$39)>0,SUMIF($A$15:$A$39,A18,$L$15:$L$39)>0),$C$11,IF(OR(SUMIF($A$15:$A$39,A18,$K$15:$K$39)>0,SUMIF($A$15:$A$39,A18,$L$15:$L$39)>0),$C$10,$C$9)))) | P18: =IF(A18="","",N18-O18) | R18: =IF(A18="","",N(H18)+N(I18)+N(J18)+N(K18)+N(L18)+N18) | S18: =IF(A18="","",IF(ISNUMBER(SEARCH("ESEMPIO",B18)),"ESEMPIO: cancellare la riga",IF(OR(F18="",C18=""),"MANCA destinazione o commessa",IF(OR(LOWER(TRIM(F18))=LOWER(TRIM($C$6)),ISNUMBER(SEARCH(","&LOWER(TRIM(F18))&",",","&LOWER(SUBSTITUTE($C$12," ",""))&","))),"NO: trasferta nel comune della sede (o frazione)",IF(AND(N(K18)+N(L18)>0,UPPER(M18)<>"S"),"NO: vitto/alloggio non tracciabile",IF(Q18<1,"MANCA prova della trasferta","OK"))))))
H19: =IF(G19="","",G19*$C$7) | N19: =IF(A19="","",IF(COUNTIF($A$15:A19,A19)=1,$C$8,0)) | O19: =IF(A19="","",MIN(N19,IF(AND(SUMIF($A$15:$A$39,A19,$K$15:$K$39)>0,SUMIF($A$15:$A$39,A19,$L$15:$L$39)>0),$C$11,IF(OR(SUMIF($A$15:$A$39,A19,$K$15:$K$39)>0,SUMIF($A$15:$A$39,A19,$L$15:$L$39)>0),$C$10,$C$9)))) | P19: =IF(A19="","",N19-O19) | R19: =IF(A19="","",N(H19)+N(I19)+N(J19)+N(K19)+N(L19)+N19) | S19: =IF(A19="","",IF(ISNUMBER(SEARCH("ESEMPIO",B19)),"ESEMPIO: cancellare la riga",IF(OR(F19="",C19=""),"MANCA destinazione o commessa",IF(OR(LOWER(TRIM(F19))=LOWER(TRIM($C$6)),ISNUMBER(SEARCH(","&LOWER(TRIM(F19))&",",","&LOWER(SUBSTITUTE($C$12," ",""))&","))),"NO: trasferta nel comune della sede (o frazione)",IF(AND(N(K19)+N(L19)>0,UPPER(M19)<>"S"),"NO: vitto/alloggio non tracciabile",IF(Q19<1,"MANCA prova della trasferta","OK"))))))
H20: =IF(G20="","",G20*$C$7) | N20: =IF(A20="","",IF(COUNTIF($A$15:A20,A20)=1,$C$8,0)) | O20: =IF(A20="","",MIN(N20,IF(AND(SUMIF($A$15:$A$39,A20,$K$15:$K$39)>0,SUMIF($A$15:$A$39,A20,$L$15:$L$39)>0),$C$11,IF(OR(SUMIF($A$15:$A$39,A20,$K$15:$K$39)>0,SUMIF($A$15:$A$39,A20,$L$15:$L$39)>0),$C$10,$C$9)))) | P20: =IF(A20="","",N20-O20) | R20: =IF(A20="","",N(H20)+N(I20)+N(J20)+N(K20)+N(L20)+N20) | S20: =IF(A20="","",IF(ISNUMBER(SEARCH("ESEMPIO",B20)),"ESEMPIO: cancellare la riga",IF(OR(F20="",C20=""),"MANCA destinazione o commessa",IF(OR(LOWER(TRIM(F20))=LOWER(TRIM($C$6)),ISNUMBER(SEARCH(","&LOWER(TRIM(F20))&",",","&LOWER(SUBSTITUTE($C$12," ",""))&","))),"NO: trasferta nel comune della sede (o frazione)",IF(AND(N(K20)+N(L20)>0,UPPER(M20)<>"S"),"NO: vitto/alloggio non tracciabile",IF(Q20<1,"MANCA prova della trasferta","OK"))))))
H21: =IF(G21="","",G21*$C$7) | N21: =IF(A21="","",IF(COUNTIF($A$15:A21,A21)=1,$C$8,0)) | O21: =IF(A21="","",MIN(N21,IF(AND(SUMIF($A$15:$A$39,A21,$K$15:$K$39)>0,SUMIF($A$15:$A$39,A21,$L$15:$L$39)>0),$C$11,IF(OR(SUMIF($A$15:$A$39,A21,$K$15:$K$39)>0,SUMIF($A$15:$A$39,A21,$L$15:$L$39)>0),$C$10,$C$9)))) | P21: =IF(A21="","",N21-O21) | R21: =IF(A21="","",N(H21)+N(I21)+N(J21)+N(K21)+N(L21)+N21) | S21: =IF(A21="","",IF(ISNUMBER(SEARCH("ESEMPIO",B21)),"ESEMPIO: cancellare la riga",IF(OR(F21="",C21=""),"MANCA destinazione o commessa",IF(OR(LOWER(TRIM(F21))=LOWER(TRIM($C$6)),ISNUMBER(SEARCH(","&LOWER(TRIM(F21))&",",","&LOWER(SUBSTITUTE($C$12," ",""))&","))),"NO: trasferta nel comune della sede (o frazione)",IF(AND(N(K21)+N(L21)>0,UPPER(M21)<>"S"),"NO: vitto/alloggio non tracciabile",IF(Q21<1,"MANCA prova della trasferta","OK"))))))
H22: =IF(G22="","",G22*$C$7) | N22: =IF(A22="","",IF(COUNTIF($A$15:A22,A22)=1,$C$8,0)) | O22: =IF(A22="","",MIN(N22,IF(AND(SUMIF($A$15:$A$39,A22,$K$15:$K$39)>0,SUMIF($A$15:$A$39,A22,$L$15:$L$39)>0),$C$11,IF(OR(SUMIF($A$15:$A$39,A22,$K$15:$K$39)>0,SUMIF($A$15:$A$39,A22,$L$15:$L$39)>0),$C$10,$C$9)))) | P22: =IF(A22="","",N22-O22) | R22: =IF(A22="","",N(H22)+N(I22)+N(J22)+N(K22)+N(L22)+N22) | S22: =IF(A22="","",IF(ISNUMBER(SEARCH("ESEMPIO",B22)),"ESEMPIO: cancellare la riga",IF(OR(F22="",C22=""),"MANCA destinazione o commessa",IF(OR(LOWER(TRIM(F22))=LOWER(TRIM($C$6)),ISNUMBER(SEARCH(","&LOWER(TRIM(F22))&",",","&LOWER(SUBSTITUTE($C$12," ",""))&","))),"NO: trasferta nel comune della sede (o frazione)",IF(AND(N(K22)+N(L22)>0,UPPER(M22)<>"S"),"NO: vitto/alloggio non tracciabile",IF(Q22<1,"MANCA prova della trasferta","OK"))))))
H23: =IF(G23="","",G23*$C$7) | N23: =IF(A23="","",IF(COUNTIF($A$15:A23,A23)=1,$C$8,0)) | O23: =IF(A23="","",MIN(N23,IF(AND(SUMIF($A$15:$A$39,A23,$K$15:$K$39)>0,SUMIF($A$15:$A$39,A23,$L$15:$L$39)>0),$C$11,IF(OR(SUMIF($A$15:$A$39,A23,$K$15:$K$39)>0,SUMIF($A$15:$A$39,A23,$L$15:$L$39)>0),$C$10,$C$9)))) | P23: =IF(A23="","",N23-O23) | R23: =IF(A23="","",N(H23)+N(I23)+N(J23)+N(K23)+N(L23)+N23) | S23: =IF(A23="","",IF(ISNUMBER(SEARCH("ESEMPIO",B23)),"ESEMPIO: cancellare la riga",IF(OR(F23="",C23=""),"MANCA destinazione o commessa",IF(OR(LOWER(TRIM(F23))=LOWER(TRIM($C$6)),ISNUMBER(SEARCH(","&LOWER(TRIM(F23))&",",","&LOWER(SUBSTITUTE($C$12," ",""))&","))),"NO: trasferta nel comune della sede (o frazione)",IF(AND(N(K23)+N(L23)>0,UPPER(M23)<>"S"),"NO: vitto/alloggio non tracciabile",IF(Q23<1,"MANCA prova della trasferta","OK"))))))
H24: =IF(G24="","",G24*$C$7) | N24: =IF(A24="","",IF(COUNTIF($A$15:A24,A24)=1,$C$8,0)) | O24: =IF(A24="","",MIN(N24,IF(AND(SUMIF($A$15:$A$39,A24,$K$15:$K$39)>0,SUMIF($A$15:$A$39,A24,$L$15:$L$39)>0),$C$11,IF(OR(SUMIF($A$15:$A$39,A24,$K$15:$K$39)>0,SUMIF($A$15:$A$39,A24,$L$15:$L$39)>0),$C$10,$C$9)))) | P24: =IF(A24="","",N24-O24) | R24: =IF(A24="","",N(H24)+N(I24)+N(J24)+N(K24)+N(L24)+N24) | S24: =IF(A24="","",IF(ISNUMBER(SEARCH("ESEMPIO",B24)),"ESEMPIO: cancellare la riga",IF(OR(F24="",C24=""),"MANCA destinazione o commessa",IF(OR(LOWER(TRIM(F24))=LOWER(TRIM($C$6)),ISNUMBER(SEARCH(","&LOWER(TRIM(F24))&",",","&LOWER(SUBSTITUTE($C$12," ",""))&","))),"NO: trasferta nel comune della sede (o frazione)",IF(AND(N(K24)+N(L24)>0,UPPER(M24)<>"S"),"NO: vitto/alloggio non tracciabile",IF(Q24<1,"MANCA prova della trasferta","OK"))))))
H25: =IF(G25="","",G25*$C$7) | N25: =IF(A25="","",IF(COUNTIF($A$15:A25,A25)=1,$C$8,0)) | O25: =IF(A25="","",MIN(N25,IF(AND(SUMIF($A$15:$A$39,A25,$K$15:$K$39)>0,SUMIF($A$15:$A$39,A25,$L$15:$L$39)>0),$C$11,IF(OR(SUMIF($A$15:$A$39,A25,$K$15:$K$39)>0,SUMIF($A$15:$A$39,A25,$L$15:$L$39)>0),$C$10,$C$9)))) | P25: =IF(A25="","",N25-O25) | R25: =IF(A25="","",N(H25)+N(I25)+N(J25)+N(K25)+N(L25)+N25) | S25: =IF(A25="","",IF(ISNUMBER(SEARCH("ESEMPIO",B25)),"ESEMPIO: cancellare la riga",IF(OR(F25="",C25=""),"MANCA destinazione o commessa",IF(OR(LOWER(TRIM(F25))=LOWER(TRIM($C$6)),ISNUMBER(SEARCH(","&LOWER(TRIM(F25))&",",","&LOWER(SUBSTITUTE($C$12," ",""))&","))),"NO: trasferta nel comune della sede (o frazione)",IF(AND(N(K25)+N(L25)>0,UPPER(M25)<>"S"),"NO: vitto/alloggio non tracciabile",IF(Q25<1,"MANCA prova della trasferta","OK"))))))
H26: =IF(G26="","",G26*$C$7) | N26: =IF(A26="","",IF(COUNTIF($A$15:A26,A26)=1,$C$8,0)) | O26: =IF(A26="","",MIN(N26,IF(AND(SUMIF($A$15:$A$39,A26,$K$15:$K$39)>0,SUMIF($A$15:$A$39,A26,$L$15:$L$39)>0),$C$11,IF(OR(SUMIF($A$15:$A$39,A26,$K$15:$K$39)>0,SUMIF($A$15:$A$39,A26,$L$15:$L$39)>0),$C$10,$C$9)))) | P26: =IF(A26="","",N26-O26) | R26: =IF(A26="","",N(H26)+N(I26)+N(J26)+N(K26)+N(L26)+N26) | S26: =IF(A26="","",IF(ISNUMBER(SEARCH("ESEMPIO",B26)),"ESEMPIO: cancellare la riga",IF(OR(F26="",C26=""),"MANCA destinazione o commessa",IF(OR(LOWER(TRIM(F26))=LOWER(TRIM($C$6)),ISNUMBER(SEARCH(","&LOWER(TRIM(F26))&",",","&LOWER(SUBSTITUTE($C$12," ",""))&","))),"NO: trasferta nel comune della sede (o frazione)",IF(AND(N(K26)+N(L26)>0,UPPER(M26)<>"S"),"NO: vitto/alloggio non tracciabile",IF(Q26<1,"MANCA prova della trasferta","OK"))))))
H27: =IF(G27="","",G27*$C$7) | N27: =IF(A27="","",IF(COUNTIF($A$15:A27,A27)=1,$C$8,0)) | O27: =IF(A27="","",MIN(N27,IF(AND(SUMIF($A$15:$A$39,A27,$K$15:$K$39)>0,SUMIF($A$15:$A$39,A27,$L$15:$L$39)>0),$C$11,IF(OR(SUMIF($A$15:$A$39,A27,$K$15:$K$39)>0,SUMIF($A$15:$A$39,A27,$L$15:$L$39)>0),$C$10,$C$9)))) | P27: =IF(A27="","",N27-O27) | R27: =IF(A27="","",N(H27)+N(I27)+N(J27)+N(K27)+N(L27)+N27) | S27: =IF(A27="","",IF(ISNUMBER(SEARCH("ESEMPIO",B27)),"ESEMPIO: cancellare la riga",IF(OR(F27="",C27=""),"MANCA destinazione o commessa",IF(OR(LOWER(TRIM(F27))=LOWER(TRIM($C$6)),ISNUMBER(SEARCH(","&LOWER(TRIM(F27))&",",","&LOWER(SUBSTITUTE($C$12," ",""))&","))),"NO: trasferta nel comune della sede (o frazione)",IF(AND(N(K27)+N(L27)>0,UPPER(M27)<>"S"),"NO: vitto/alloggio non tracciabile",IF(Q27<1,"MANCA prova della trasferta","OK"))))))
... H39: =IF(G39="","",G39*$C$7) | N39: =IF(A39="","",IF(COUNTIF($A$15:A39,A39)=1,$C$8,0)) | O39: =IF(A39="","",MIN(N39,IF(AND(SUMIF($A$15:$A$39,A39,$K$15:$K$39)>0,SUMIF($A$15:$A$39,A39,$L$15:$L$39)>0),$C$11,IF(OR(SUMIF($A$15:$A$39,A39,$K$15:$K$39)>0,SUMIF($A$15:$A$39,A39,$L$15:$L$39)>0),$C$10,$C$9)))) | P39: =IF(A39="","",N39-O39) | R39: =IF(A39="","",N(H39)+N(I39)+N(J39)+N(K39)+N(L39)+N39) | S39: =IF(A39="","",IF(ISNUMBER(SEARCH("ESEMPIO",B39)),"ESEMPIO: cancellare la riga",IF(OR(F39="",C39=""),"MANCA destinazione o commessa",IF(OR(LOWER(TRIM(F39))=LOWER(TRIM($C$6)),ISNUMBER(SEARCH(","&LOWER(TRIM(F39))&",",","&LOWER(SUBSTITUTE($C$12," ",""))&","))),"NO: trasferta nel comune della sede (o frazione)",IF(AND(N(K39)+N(L39)>0,UPPER(M39)<>"S"),"NO: vitto/alloggio non tracciabile",IF(Q39<1,"MANCA prova della trasferta","OK"))))))
F41: TOTALI | G41: =SUM(G15:G39) | H41: =SUM(H15:H39) | I41: =SUM(I15:I39) | J41: =SUM(J15:J39) | K41: =SUM(K15:K39) | L41: =SUM(L15:L39) | N41: =SUM(N15:N39) | O41: =SUM(O15:O39) | P41: =SUM(P15:P39) | R41: =SUM(R15:R39)
F42: DA PAGARE (solo righe OK) | R42: =SUMIFS(R15:R39,S15:S39,"OK")
F43: di cui da tassare in cedolino (indennità oltre soglia, righe OK) | R43: =SUMIFS(P15:P39,S15:S39,"OK")
F44: Righe da correggere prima dell'approvazione | R44: =SUMPRODUCT((S15:S39<>"")*(LEFT(S15:S39,2)<>"OK"))
A47: Firma del beneficiario e data
A49: Approvato da (altro amministratore), firma e data
A51: Pagato con bonifico il / CRO
A53: Riportato nel cedolino del mese, voce

Sheet Istruzioni
A1: COME COMPILARE (5 minuti al mese)
A2: 1. Celle gialle = da compilare. Celle grigie e bianche = calcolate, non toccare.
A3: 2. Intestazione: si compila una volta sola; aggiornare il mese, e la tariffa ACI solo se cambia il veicolo.
A4: 3. Una riga per ogni trasferta, il giorno stesso o a fine settimana. La riga azzurra è un esempio: cancellarla.
A5: 4. Colonna «Controllo»: deve dire OK su ogni riga. Se è rossa, correggere o eliminare la riga prima di firmare.
A6: 5. A fine mese: salvare in PDF, firmare, far approvare da un altro amministratore, allegare i documenti, pagare con bonifico l'importo «TOTALE RIMBORSABILE».
A8: COSA SI INSERISCE IN OGNI COLONNA
A9: Data: giorno della trasferta. Cliente e Commessa: cliente servito e riferimento verificabile (commessa o fattura FatturaLab, verbale, mail).
A10: Motivo: attività svolta (sopralluogo, corso, riunione, audit...). Mai generico («varie», «clienti»).
A11: Partenza: normalmente la sede di Villafranca. Se si parte da casa (Verona), indicare Verona e usare i km più brevi fra casa-cliente e sede-cliente.
A12: Destinazione: il COMUNE del cliente, non la frazione né la via. Deve essere diverso da Villafranca di Verona e dalle sue frazioni (Alpo, Caluri, Dossobuono, Pizzoletta, Quaderni, Rizza, Rosegaferro): il controllo le riconosce [elenco da confermare].
A13: Km andata e ritorno: distanza reale del percorso (stampare il percorso da Google Maps o simile e allegarlo).
... A35: Modello predisposto il 25/09/2026. Tariffa di esempio 0,45 €/km: sostituirla con il valore ACI del veicolo effettivo.
